geonumpy/__init__.py
geonumpy/base/__init__.py
geonumpy/base/geonumpy.py
geonumpy/download/__init__.py
geonumpy/download/landsat_download.py
geonumpy/download/landsat_search.py
geonumpy/download/modis_download.py
geonumpy/download/tile_online_download.py
geonumpy/draw/__init__.py
geonumpy/draw/draw.py
geonumpy/io/__init__.py
geonumpy/io/geoio.py
geonumpy/match/__init__.py
geonumpy/match/match.py
geonumpy/pretreat/__init__.py
geonumpy/pretreat/gaprepair.py
geonumpy/util/__init__.py
geonumpy/util/util.py
geonumpy-0.10.dist-info/LICENSE
geonumpy-0.10.dist-info/METADATA
geonumpy-0.10.dist-info/WHEEL
geonumpy-0.10.dist-info/top_level.txt
geonumpy-0.10.dist-info/RECORD
